GmailAPIHelper.py
GmailAPIHelper-0.0.1.dist-info/LICENSE.md
GmailAPIHelper-0.0.1.dist-info/WHEEL
GmailAPIHelper-0.0.1.dist-info/METADATA
GmailAPIHelper-0.0.1.dist-info/RECORD
