Metadata-Version: 1.2
Name: GmailAPIHelper
Version: 0.0.1
Summary: Module to help navigate the Gmail API responses
Home-page: https://github.com/ACarrasco1009/GmailAPIHelper
License: UNKNOWN
Keywords: gmail api
Author: Alec Carrasco
Author-email: alecc1009@gmail.com
Classifier: Development Status :: 3 - Alpha
Classifier: Intended Audience :: Developers
Classifier: License :: OSI Approved :: MIT License
Classifier: Operating System :: Microsoft :: Windows :: Windows 10
Classifier: Programming Language :: Python :: 3.6
Classifier: Topic :: Utilities
Requires-Dist: google-api-python-client (>= 1.6.2)
Requires-Dist: pytz (>= 2017.2)
